pya2/__init__.py
pya2-0.0.1.dist-info/WHEEL
pya2-0.0.1.dist-info/METADATA
pya2-0.0.1.dist-info/RECORD
