Metadata-Version: 2.1
Name: pya2
Version: 0.0.1
Summary: Python Ann Arbor
License: MIT
Author: Elijah Wilson
Author-email: dev.tizz98@gmail.com
Requires-Python: >=3.10,<4.0
Classifier: License :: OSI Approved :: MIT License
Classifier: Programming Language :: Python :: 3
Classifier: Programming Language :: Python :: 3.10
